tcai_churn_x/__init__.py
tcai_churn_x/__main__.py
tcai_churn_x/webapp.py
tcai_churn_x/model/best_model.pkl
tcai_churn_x/model/encoder.pkl
tcai_churn_x/model/scaler.pkl
tcai_churn_x/templates/index.html
tcai_churn_x-0.1.1.dist-info/METADATA
tcai_churn_x-0.1.1.dist-info/WHEEL
tcai_churn_x-0.1.1.dist-info/entry_points.txt
tcai_churn_x-0.1.1.dist-info/top_level.txt
tcai_churn_x-0.1.1.dist-info/RECORD
