Metadata-Version: 2.4
Name: tcai-churn-x
Version: 0.1.1
Summary: A Flask-based web app for predicting customer churn using a trained ML model.
Author: The Celeritas AI
Author-email: business@theceleritasai.com
Classifier: Programming Language :: Python :: 3
Classifier: Framework :: Flask
Classifier: License :: OSI Approved :: MIT License
Classifier: Operating System :: OS Independent
Requires-Python: >=3.8
Requires-Dist: Flask==3.1.1
Requires-Dist: pandas==2.3.0
Requires-Dist: numpy==2.3.0
Requires-Dist: scikit-learn==1.6.1
Requires-Dist: joblib==1.5.1
Requires-Dist: python-dateutil==2.9.0.post0
Requires-Dist: Werkzeug==3.1.3
Requires-Dist: Jinja2==3.1.6
Dynamic: author
Dynamic: author-email
Dynamic: classifier
Dynamic: description
Dynamic: description-content-type
Dynamic: requires-dist
Dynamic: requires-python
Dynamic: summary
